dtu_compute/__init__.py
dtu_compute/auth.py
dtu_compute/cli.py
dtu_compute/config.py
dtu_compute/connection.py
dtu_compute/run_config.py
dtu_compute/sweep.py
dtu_compute/utils.py
dtu_compute/hpc/__init__.py
dtu_compute/hpc/cli.py
dtu_compute/hpc/registry.py
dtu_compute/hpc/submit.py
dtu_compute/llm/__init__.py
dtu_compute/llm/cli.py
dtu_compute/titans/__init__.py
dtu_compute/titans/cli.py
dtu_compute/titans/registry.py
dtu_compute/titans/submit.py
dtu_compute-0.0.3.dist-info/METADATA
dtu_compute-0.0.3.dist-info/WHEEL
dtu_compute-0.0.3.dist-info/entry_points.txt
dtu_compute-0.0.3.dist-info/licenses/LICENSE
dtu_compute-0.0.3.dist-info/RECORD
